UNKnownDB-1.6.7.data/scripts/start.py
UsefulHelper/__init__.py
UsefulHelper/cli.py
UsefulHelper/Tools/__init__.py
UNKnownDB-1.6.7.dist-info/LICENSE
UNKnownDB-1.6.7.dist-info/METADATA
UNKnownDB-1.6.7.dist-info/WHEEL
UNKnownDB-1.6.7.dist-info/top_level.txt
UNKnownDB-1.6.7.dist-info/RECORD
