Metadata-Version: 2.1
Name: UNKnownDB
Version: 1.6.7
Summary: A new Python DB
Home-page: https://github.com/CleverCreater/UNKnownDB
Author: CleaverCreator
Author-email: liuhanbo333@icloud.com
License: GIL
Platform: Linux
Requires-Python: >=3.9
Requires-Dist: PyQt5
